borneo_python_client/__init__.py
borneo_python_client/auth.py
borneo_python_client/client.py
borneo_python_client/config.py
borneo_python_client/deserialize.py
borneo_python_client/errors.py
borneo_python_client/models.py
borneo_python_client/serialize.py
smithy_aws_core/BUILD
smithy_aws_core/__init__.py
smithy_aws_core/identity.py
smithy_aws_core/py.typed
smithy_aws_core/interfaces/__init__.py
smithy_core/BUILD
smithy_core/__init__.py
smithy_core/documents.py
smithy_core/exceptions.py
smithy_core/identity.py
smithy_core/interceptors.py
smithy_core/py.typed
smithy_core/retries.py
smithy_core/rfc3986.py
smithy_core/schemas.py
smithy_core/shapes.py
smithy_core/traits.py
smithy_core/types.py
smithy_core/utils.py
smithy_core/aio/__init__.py
smithy_core/aio/types.py
smithy_core/aio/utils.py
smithy_core/aio/interfaces/__init__.py
smithy_core/aio/interfaces/identity.py
smithy_core/interfaces/__init__.py
smithy_core/interfaces/exceptions.py
smithy_core/interfaces/identity.py
smithy_core/interfaces/retries.py
smithy_http/BUILD
smithy_http/__init__.py
smithy_http/endpoints.py
smithy_http/exceptions.py
smithy_http/py.typed
smithy_http/restjson.py
smithy_http/utils.py
smithy_http/aio/__init__.py
smithy_http/aio/aiohttp.py
smithy_http/aio/crt.py
smithy_http/aio/endpoints.py
smithy_http/aio/restjson.py
smithy_http/aio/auth/__init__.py
smithy_http/aio/auth/apikey.py
smithy_http/aio/identity/__init__.py
smithy_http/aio/identity/apikey.py
smithy_http/aio/interfaces/__init__.py
smithy_http/aio/interfaces/auth.py
smithy_http/interfaces/__init__.py
borneo_python_client-3.10.3.dist-info/LICENSE
borneo_python_client-3.10.3.dist-info/METADATA
borneo_python_client-3.10.3.dist-info/WHEEL
borneo_python_client-3.10.3.dist-info/top_level.txt
borneo_python_client-3.10.3.dist-info/RECORD
