Metadata-Version: 2.1
Name: borneo_python_client
Version: 3.10.3
Summary: borneo_python_client client
License: Apache-2.0
Keywords: smithy,borneo_python_client
Classifier: Development Status :: 2 - Pre-Alpha
Classifier: Intended Audience :: Developers
Classifier: Intended Audience :: System Administrators
Classifier: Natural Language :: English
Classifier: License :: OSI Approved :: Apache Software License
Classifier: Programming Language :: Python
Classifier: Programming Language :: Python :: 3
Classifier: Programming Language :: Python :: 3 :: Only
Classifier: Programming Language :: Python :: 3.12
Requires-Python: >=3.12
License-File: LICENSE
Provides-Extra: tests
Requires-Dist: pytest <8.0.0,>=7.2.0 ; extra == 'tests'
Requires-Dist: pytest-asyncio <0.21.0,>=0.20.3 ; extra == 'tests'
